pychron/__init__.py
pychron/cli.py
pychron-0.1.1.dist-info/licenses/LICENSE
pychron-0.1.1.dist-info/METADATA
pychron-0.1.1.dist-info/WHEEL
pychron-0.1.1.dist-info/entry_points.txt
pychron-0.1.1.dist-info/top_level.txt
pychron-0.1.1.dist-info/RECORD
