Metadata-Version: 2.4
Name: pychron
Version: 0.1.1
Summary: A helper tool that shows the execution time while running Python scripts
Author-email: Muslu Yüksektepe <musluyuksektepe@gmail.com>, Ali Alın <alialinxz@gmail.com>
Maintainer-email: Ali Alın2 <alialinxz@gmail.com>
License: MIT
Keywords: timer,cli,python,execution,time
Requires-Python: >=3.9
License-File: LICENSE
Dynamic: license-file
